google_functionregistry/__init__.py
google_functionregistry/client.py
google_functionregistry/generate_pydantic_model.py
google_functionregistry/tool_registry.py
google_functionregistry/tool_registry_usage_example.py
google_functionregistry/utils.py
google_functionregistry-0.2.6.dist-info/LICENSE
google_functionregistry-0.2.6.dist-info/METADATA
google_functionregistry-0.2.6.dist-info/WHEEL
google_functionregistry-0.2.6.dist-info/RECORD
